src/__init__.py
src/gencommit.py
src/utils/config.py
src/utils/llm_wrapper.py
src/utils/prompts.py
gen_commit-1.0.0.dist-info/METADATA
gen_commit-1.0.0.dist-info/WHEEL
gen_commit-1.0.0.dist-info/entry_points.txt
gen_commit-1.0.0.dist-info/licenses/LICENSE
gen_commit-1.0.0.dist-info/RECORD
