Metadata-Version: 2.4
Name: gen-commit
Version: 1.0.0
Summary: Auto-generate git commit messages
Project-URL: Homepage, https://github.com/raghavpillai/gen-commit
Project-URL: Issues, https://github.com/raghavpillai/gen-commit/issues
Author-email: Raghav Pillai <me@raghav.sh>
License: MIT License
License-File: LICENSE
Classifier: License :: OSI Approved :: MIT License
Classifier: Operating System :: OS Independent
Classifier: Programming Language :: Python :: 3
Requires-Python: >=3.11
Requires-Dist: openai
Requires-Dist: tiktoken>=0.9.0
Requires-Dist: tomli
